dressuplite/__init__.py
dressuplite/converter.py
dressuplite/exceptions.py
dressuplite/translator.toml
dressuplite-0.1.2.dist-info/LICENSE
dressuplite-0.1.2.dist-info/METADATA
dressuplite-0.1.2.dist-info/WHEEL
dressuplite-0.1.2.dist-info/top_level.txt
dressuplite-0.1.2.dist-info/RECORD
