Metadata-Version: 2.1
Name: dressuplite
Version: 0.1.2
Summary: Dependency-free lightweight fork of the package "dressup" to convert strings to use Unicode formatting
Home-page: https://github.com/impredicative/dressuplite/
Author: Ouroboros Chrysopoeia
Author-email: impredicative@users.nomail.github.com
Keywords: unicode text
Classifier: Programming Language :: Python :: 3.11
Classifier: Topic :: Text Processing :: General
Classifier: Topic :: Software Development :: Libraries :: Python Modules
Requires-Python: >=3.11
License-File: LICENSE
